slicer_tools/__init__.py
slicer_tools/common.py
slicer_tools/presets.py
slicer_tools/tools.py
bambu_slicer_tools-0.9.2.dist-info/METADATA
bambu_slicer_tools-0.9.2.dist-info/WHEEL
bambu_slicer_tools-0.9.2.dist-info/licenses/LICENSE
bambu_slicer_tools-0.9.2.dist-info/RECORD
