Metadata-Version: 2.4
Name: bambu_slicer_tools
Version: 0.9.2
Summary: Tools for working with 3D slicer (.3mf) files. Currently focussed on Bambu Studio.
Project-URL: Homepage, https://github.com/BuongiornoTexas/slicer_tools
Project-URL: Bug Tracker, https://github.com/BuongiornoTexas/slicer_tools/issues
Author: BuongiornoTexas
License-File: LICENSE
Keywords: 3D Slicer,3D file comparison,3mf comparison,Bambu Studio
Classifier: License :: OSI Approved :: MIT License
Classifier: Operating System :: OS Independent
Classifier: Programming Language :: Python :: 3
Requires-Python: >=3.13
Requires-Dist: openpyxl
